{
  "cpa": "https://www.google.com/",
  "data": [
      {
        "title": "First One",
        "profile": "https://i.pinimg.com/736x/59/37/5f/59375f2046d3b594d59039e8ffbf485a.jpg",
        "age": "28",
        "gender": "Female",
        "country": "https://upload.wikimedia.org/wikipedia/commons/thumb/f/fe/Flag_of_Egypt.svg/510px-Flag_of_Egypt.svg.png",
        "desc": "First Description Here",
        "fbPage": "https://www.facebook.com/",
        "igPage": "https://www.instagram.com/",
        "whatsapp": "+1 901 789 1212"
      },
    {
        "title": "First One",
        "profile": "https://i.pinimg.com/736x/59/37/5f/59375f2046d3b594d59039e8ffbf485a.jpg",
        "age": "24",
        "gender": "Male",
        "country": "https://upload.wikimedia.org/wikipedia/commons/thumb/f/fe/Flag_of_Egypt.svg/510px-Flag_of_Egypt.svg.png",
        "desc": "First Description Here",
        "fbPage": "https://www.facebook.com/",
        "igPage": "https://www.instagram.com/",
        "whatsapp": "+1 901 789 1212"
      },
    {
        "title": "First One",
        "profile": "https://i.pinimg.com/736x/59/37/5f/59375f2046d3b594d59039e8ffbf485a.jpg",
        "age": "28",
        "gender": "Female",
        "country": "https://upload.wikimedia.org/wikipedia/commons/thumb/f/fe/Flag_of_Egypt.svg/510px-Flag_of_Egypt.svg.png",
        "desc": "First Description Here",
        "fbPage": "https://www.facebook.com/",
        "igPage": "https://www.instagram.com/",
        "whatsapp": "+1 901 789 1212"
      },
    {
        "title": "First One",
        "profile": "https://i.pinimg.com/736x/59/37/5f/59375f2046d3b594d59039e8ffbf485a.jpg",
        "age": "28",
        "gender": "Female",
        "country": "https://upload.wikimedia.org/wikipedia/commons/thumb/f/fe/Flag_of_Egypt.svg/510px-Flag_of_Egypt.svg.png",
        "desc": "First Description Here",
        "fbPage": "https://www.facebook.com/",
        "igPage": "https://www.instagram.com/",
        "whatsapp": "+1 901 789 1212"
      }
    ]
}
